langchain_test5/__init__.py
langchain_test5/embeddings.py
langchain_test5/py.typed
langchain_test5/query_constructors.py
langchain_test5/utils.py
langchain_test5/vectorstores.py
langchain_test5-0.1.0.dist-info/LICENSE
langchain_test5-0.1.0.dist-info/LICENSES/Apache-2.0.txt
langchain_test5-0.1.0.dist-info/METADATA
langchain_test5-0.1.0.dist-info/WHEEL
langchain_test5-0.1.0.dist-info/RECORD
